chromatopy/FID/FID_General.py
chromatopy/FID/FID_Integration_functions.py
chromatopy/FID/FID_integration.py
chromatopy/FID/Tools.py
chromatopy/FID/__init__.py
chromatopy/FID/bouqueter.py
chromatopy/FID/import_data.py
chromatopy/FID/manual_peak_integration.py
chromatopy/FID/peak_labels.json
chromatopy/FID/peak_labels_editor.py
chromatopy/__init__.py
chromatopy/assign_indices.py
chromatopy/chromatoPy.py
chromatopy/chromatoPy_base.py
chromatopy/hplc_integration.py
chromatopy/hplc_to_csv.py
chromatopy/utils/GDGT_compounds.py
chromatopy/utils/calculate_indices.py
chromatopy/utils/chromatoPy_preprocess.py
chromatopy/utils/compounds.py
chromatopy/utils/errors/smoothing_check.py
chromatopy/utils/folder_handling.py
chromatopy/utils/handle_window_params.py
chromatopy/utils/import_data.py
chromatopy/utils/messages.py
chromatopy/utils/time_normalization.py
chromatopy-2.0.0.dist-info/LICENSE
chromatopy-2.0.0.dist-info/METADATA
chromatopy-2.0.0.dist-info/WHEEL
chromatopy-2.0.0.dist-info/RECORD
