Metadata-Version: 2.3
Name: chromatopy
Version: 2.0.0
Summary: Peak integration software.
Author: Dr. Gerard Otiniano
Author-email: gerardotiniano@gmail.com
Requires-Python: >=3.11,<4.0
Classifier: Programming Language :: Python :: 3
Classifier: Programming Language :: Python :: 3.11
Classifier: Programming Language :: Python :: 3.12
Classifier: Programming Language :: Python :: 3.13
Requires-Dist: ImageHash (==4.3.2)
Requires-Dist: Pillow (==11.3.0)
Requires-Dist: PyQt5 (==5.15.11)
Requires-Dist: PyQt5_sip (==12.17.0)
Requires-Dist: hdbscan (==0.8.40)
Requires-Dist: ipywidgets (>=8,<9)
Requires-Dist: matplotlib (==3.10.5)
Requires-Dist: numpy (==2.3.2)
Requires-Dist: pandas (==2.3.1)
Requires-Dist: pybaselines (==1.1.0)
Requires-Dist: rainbow_api (==1.0.9)
Requires-Dist: scikit_learn (==1.7.1)
Requires-Dist: scipy (==1.16.1)
Requires-Dist: tqdm (==4.67.1)
